{
  "yaakVersion": "2025.4.0",
  "yaakSchema": 4,
  "timestamp": "2025-07-10T20:18:05.030722200",
  "resources": {
    "workspaces": [
      {
        "model": "workspace",
        "id": "wk_E9kD4NLtfq",
        "createdAt": "2025-07-08T15:40:47.315477300",
        "updatedAt": "2025-07-08T15:40:47.315478",
        "authentication": {},
        "authenticationType": null,
        "description": "",
        "headers": [],
        "name": "MyWhiskyShelf",
        "encryptionKeyChallenge": null,
        "settingValidateCertificates": true,
        "settingFollowRedirects": true,
        "settingRequestTimeout": 0
      }
    ],
    "environments": [
      {
        "model": "environment",
        "id": "ev_4qY6kSvw9X",
        "workspaceId": "wk_E9kD4NLtfq",
        "createdAt": "2025-07-08T15:44:44.664097800",
        "updatedAt": "2025-07-08T16:07:13.474976800",
        "name": "Development",
        "public": true,
        "base": false,
        "variables": [
          {
            "enabled": true,
            "name": "host",
            "value": "localhost:5016",
            "id": "AafgWtiKcW"
          }
        ],
        "color": null
      }
    ],
    "folders": [
      {
        "model": "folder",
        "id": "fl_D89PqEYwQg",
        "createdAt": "2025-07-10T20:01:18.588451",
        "updatedAt": "2025-07-10T20:01:18.588451600",
        "workspaceId": "wk_E9kD4NLtfq",
        "folderId": "fl_vr5hv9qtjH",
        "authentication": {},
        "authenticationType": null,
        "description": "",
        "headers": [],
        "name": "Remove existing distillery",
        "sortPriority": -1752177700000.0
      },
      {
        "model": "folder",
        "id": "fl_RiY8GMkMDb",
        "createdAt": "2025-07-10T20:00:41.511000500",
        "updatedAt": "2025-07-10T20:00:41.511001200",
        "workspaceId": "wk_E9kD4NLtfq",
        "folderId": "fl_vr5hv9qtjH",
        "authentication": {},
        "authenticationType": null,
        "description": "",
        "headers": [],
        "name": "Add new distillery",
        "sortPriority": -1752177700000.0
      },
      {
        "model": "folder",
        "id": "fl_2SUEHQ8n7W",
        "createdAt": "2025-07-10T20:00:06.175881300",
        "updatedAt": "2025-07-10T20:00:06.175881700",
        "workspaceId": "wk_E9kD4NLtfq",
        "folderId": "fl_Zi75WXkdYA",
        "authentication": {},
        "authenticationType": null,
        "description": "",
        "headers": [],
        "name": "Try to add existing distillery",
        "sortPriority": -1752177600000.0
      },
      {
        "model": "folder",
        "id": "fl_joTmTwbCZo",
        "createdAt": "2025-07-10T19:59:26.115835200",
        "updatedAt": "2025-07-10T19:59:26.115835700",
        "workspaceId": "wk_E9kD4NLtfq",
        "folderId": "fl_Zi75WXkdYA",
        "authentication": {},
        "authenticationType": null,
        "description": "",
        "headers": [],
        "name": "Try to remove existing distillery",
        "sortPriority": -1752177600000.0
      },
      {
        "model": "folder",
        "id": "fl_Zi75WXkdYA",
        "createdAt": "2025-07-08T15:44:27.472382600",
        "updatedAt": "2025-07-08T16:48:14.022762900",
        "workspaceId": "wk_E9kD4NLtfq",
        "folderId": "fl_xRp9JC6bVY",
        "authentication": {},
        "authenticationType": null,
        "description": "",
        "headers": [],
        "name": "Unhappy Path",
        "sortPriority": 1000.0
      },
      {
        "model": "folder",
        "id": "fl_vr5hv9qtjH",
        "createdAt": "2025-07-08T15:44:21.497776900",
        "updatedAt": "2025-07-08T16:48:19.332771800",
        "workspaceId": "wk_E9kD4NLtfq",
        "folderId": "fl_xRp9JC6bVY",
        "authentication": {},
        "authenticationType": null,
        "description": "",
        "headers": [],
        "name": "Happy Path",
        "sortPriority": 500.0
      },
      {
        "model": "folder",
        "id": "fl_xRp9JC6bVY",
        "createdAt": "2025-07-08T15:43:54.707700",
        "updatedAt": "2025-07-08T15:43:54.707700500",
        "workspaceId": "wk_E9kD4NLtfq",
        "folderId": null,
        "authentication": {},
        "authenticationType": null,
        "description": "",
        "headers": [],
        "name": "Distilleries",
        "sortPriority": -1751989500000.0
      }
    ],
    "httpRequests": [
      {
        "model": "http_request",
        "id": "rq_LLHh8ivYgK",
        "createdAt": "2025-07-10T19:38:57.064459",
        "updatedAt": "2025-07-10T19:59:37.652766",
        "workspaceId": "wk_E9kD4NLtfq",
        "folderId": "fl_joTmTwbCZo",
        "authentication": {},
        "authenticationType": null,
        "body": {},
        "bodyType": null,
        "description": "",
        "headers": [],
        "method": "DELETE",
        "name": "Try to remove Distillery",
        "sortPriority": 1000.0,
        "url": "${[ host ]}/distilleries/remove/FakeDistillery",
        "urlParameters": []
      },
      {
        "model": "http_request",
        "id": "rq_nDHUqSnqvh",
        "createdAt": "2025-07-10T19:38:57.064344100",
        "updatedAt": "2025-07-10T19:59:37.646108900",
        "workspaceId": "wk_E9kD4NLtfq",
        "folderId": "fl_joTmTwbCZo",
        "authentication": {},
        "authenticationType": null,
        "body": {},
        "bodyType": null,
        "description": "",
        "headers": [],
        "method": "GET",
        "name": "Get distillery by name",
        "sortPriority": 0.0,
        "url": "${[ host ]}/distilleries/FakeDistillery",
        "urlParameters": []
      },
      {
        "model": "http_request",
        "id": "rq_XbfvJccxjN",
        "createdAt": "2025-07-10T19:36:07.509380900",
        "updatedAt": "2025-07-10T20:01:38.577007600",
        "workspaceId": "wk_E9kD4NLtfq",
        "folderId": "fl_D89PqEYwQg",
        "authentication": {},
        "authenticationType": null,
        "body": {
          "text": "  {\n    \"distilleryName\": \"Aberargie\",\n    \"location\": \"Aberargie\",\n    \"region\": \"Lowland\",\n    \"founded\": 2017,\n    \"owner\": \"Perth Distilling Co\",\n    \"distilleryType\": \"Malt\",\n    \"flavourProfile\": {\n      \"sweet\": 0,\n      \"fruit\": 1,\n      \"floral\": 0,\n      \"body\": 0,\n      \"smoke\": 0,\n      \"tobacco\": 0,\n      \"medicinal\": 0,\n      \"wine\": 0,\n      \"spice\": 2,\n      \"malt\": 2,\n      \"nut\": 2,\n      \"honey\": 0\n    },\n    \"active\": true\n  }"
        },
        "bodyType": "application/json",
        "description": "",
        "headers": [
          {
            "enabled": true,
            "name": "Content-Type",
            "value": "application/json",
            "id": "4fQdDrbnSr"
          }
        ],
        "method": "POST",
        "name": "Re-add removed distillery",
        "sortPriority": 3000.0,
        "url": "${[ host ]}/distilleries/add",
        "urlParameters": []
      },
      {
        "model": "http_request",
        "id": "rq_xaATF6j2LM",
        "createdAt": "2025-07-10T19:35:59.706048",
        "updatedAt": "2025-07-10T20:01:31.973803600",
        "workspaceId": "wk_E9kD4NLtfq",
        "folderId": "fl_D89PqEYwQg",
        "authentication": {},
        "authenticationType": null,
        "body": {},
        "bodyType": null,
        "description": "",
        "headers": [],
        "method": "GET",
        "name": "Get distillery by name",
        "sortPriority": 2000.0,
        "url": "${[ host ]}/distilleries/Aberargie",
        "urlParameters": []
      },
      {
        "model": "http_request",
        "id": "rq_ndWXV7SKXd",
        "createdAt": "2025-07-10T19:35:48.553120",
        "updatedAt": "2025-07-10T20:00:59.774125400",
        "workspaceId": "wk_E9kD4NLtfq",
        "folderId": "fl_RiY8GMkMDb",
        "authentication": {},
        "authenticationType": null,
        "body": {},
        "bodyType": null,
        "description": "",
        "headers": [],
        "method": "DELETE",
        "name": "Remove added distillery",
        "sortPriority": 3000.0,
        "url": "${[ host ]}/distilleries/remove/Burn%20O%27Bennie",
        "urlParameters": []
      },
      {
        "model": "http_request",
        "id": "rq_esAqNAguaH",
        "createdAt": "2025-07-10T19:35:32.084104300",
        "updatedAt": "2025-07-10T20:01:31.961806700",
        "workspaceId": "wk_E9kD4NLtfq",
        "folderId": "fl_D89PqEYwQg",
        "authentication": {},
        "authenticationType": null,
        "body": {},
        "bodyType": null,
        "description": "",
        "headers": [],
        "method": "GET",
        "name": "Get distillery by name",
        "sortPriority": 0.0,
        "url": "${[ host ]}/distilleries/Aberargie",
        "urlParameters": []
      },
      {
        "model": "http_request",
        "id": "rq_Lzi5Y3JvNn",
        "createdAt": "2025-07-08T22:56:49.948591400",
        "updatedAt": "2025-07-10T20:01:31.969332",
        "workspaceId": "wk_E9kD4NLtfq",
        "folderId": "fl_D89PqEYwQg",
        "authentication": {},
        "authenticationType": null,
        "body": {},
        "bodyType": null,
        "description": "",
        "headers": [],
        "method": "DELETE",
        "name": "Remove distillery",
        "sortPriority": 1000.0,
        "url": "${[ host ]}/distilleries/remove/Aberargie",
        "urlParameters": []
      },
      {
        "model": "http_request",
        "id": "rq_XxDobBn495",
        "createdAt": "2025-07-08T16:47:47.456726100",
        "updatedAt": "2025-07-10T20:00:59.769294300",
        "workspaceId": "wk_E9kD4NLtfq",
        "folderId": "fl_RiY8GMkMDb",
        "authentication": {},
        "authenticationType": null,
        "body": {},
        "bodyType": null,
        "description": "",
        "headers": [],
        "method": "GET",
        "name": "Get distillery by name",
        "sortPriority": 2000.0,
        "url": "${[ host ]}/distilleries/Burn%20O%27Bennie",
        "urlParameters": []
      },
      {
        "model": "http_request",
        "id": "rq_zR6gA6bbjn",
        "createdAt": "2025-07-08T16:47:26.140824600",
        "updatedAt": "2025-07-10T20:00:59.749748700",
        "workspaceId": "wk_E9kD4NLtfq",
        "folderId": "fl_RiY8GMkMDb",
        "authentication": {},
        "authenticationType": null,
        "body": {},
        "bodyType": null,
        "description": "",
        "headers": [],
        "method": "GET",
        "name": "Get distillery by name",
        "sortPriority": 0.0,
        "url": "${[ host ]}/distilleries/Burn%20O%27Bennie",
        "urlParameters": []
      },
      {
        "model": "http_request",
        "id": "rq_AiAhdqvUab",
        "createdAt": "2025-07-08T16:46:49.541230200",
        "updatedAt": "2025-07-10T20:00:19.767678600",
        "workspaceId": "wk_E9kD4NLtfq",
        "folderId": "fl_2SUEHQ8n7W",
        "authentication": {},
        "authenticationType": null,
        "body": {},
        "bodyType": null,
        "description": "",
        "headers": [],
        "method": "GET",
        "name": "Get distillery by name",
        "sortPriority": 0.0,
        "url": "${[ host ]}/distilleries/Aberargie",
        "urlParameters": []
      },
      {
        "model": "http_request",
        "id": "rq_DwDMFwz4sZ",
        "createdAt": "2025-07-08T16:45:38.042172100",
        "updatedAt": "2025-07-10T19:58:00.012175300",
        "workspaceId": "wk_E9kD4NLtfq",
        "folderId": "fl_Zi75WXkdYA",
        "authentication": {},
        "authenticationType": null,
        "body": {},
        "bodyType": null,
        "description": "",
        "headers": [],
        "method": "GET",
        "name": "Get distillery by name",
        "sortPriority": 31.25,
        "url": "${[ host ]}/distilleries/MadeUpName",
        "urlParameters": []
      },
      {
        "model": "http_request",
        "id": "rq_uxuXpUTUvt",
        "createdAt": "2025-07-08T16:43:12.060270900",
        "updatedAt": "2025-07-10T19:58:11.953149600",
        "workspaceId": "wk_E9kD4NLtfq",
        "folderId": "fl_vr5hv9qtjH",
        "authentication": {},
        "authenticationType": null,
        "body": {},
        "bodyType": null,
        "description": "",
        "headers": [],
        "method": "GET",
        "name": "Get distillery by name",
        "sortPriority": 4000.0,
        "url": "${[ host ]}/distilleries/Aberfeldy",
        "urlParameters": []
      },
      {
        "model": "http_request",
        "id": "rq_GKWfi2bTkD",
        "createdAt": "2025-07-08T15:53:21.071337100",
        "updatedAt": "2025-07-10T20:00:19.776426100",
        "workspaceId": "wk_E9kD4NLtfq",
        "folderId": "fl_2SUEHQ8n7W",
        "authentication": {},
        "authenticationType": null,
        "body": {
          "text": "{\n    \"distilleryName\": \"Aberargie\",\n    \"location\": \"Aberargie\",\n    \"region\": \"Lowland\",\n    \"founded\": 2017,\n    \"owner\": \"Perth Distilling Co\",\n    \"distilleryType\": \"Malt\",\n    \"flavourProfile\": {\n      \"sweet\": 0,\n      \"fruit\": 1,\n      \"floral\": 0,\n      \"body\": 0,\n      \"smoke\": 0,\n      \"tobacco\": 0,\n      \"medicinal\": 0,\n      \"wine\": 0,\n      \"spice\": 2,\n      \"malt\": 2,\n      \"nut\": 2,\n      \"honey\": 0\n    },\n    \"active\": true\n  }"
        },
        "bodyType": "application/json",
        "description": "",
        "headers": [
          {
            "enabled": true,
            "name": "Content-Type",
            "value": "application/json",
            "id": "4fQdDrbnSr"
          }
        ],
        "method": "POST",
        "name": "Try to add new distillery",
        "sortPriority": 1000.0,
        "url": "${[ host ]}/distilleries/add",
        "urlParameters": []
      },
      {
        "model": "http_request",
        "id": "rq_fpZae9M5ou",
        "createdAt": "2025-07-08T15:48:09.499217700",
        "updatedAt": "2025-07-10T20:00:59.764199300",
        "workspaceId": "wk_E9kD4NLtfq",
        "folderId": "fl_RiY8GMkMDb",
        "authentication": {},
        "authenticationType": null,
        "body": {
          "text": "  {\n    \"distilleryName\": \"Burn O'Bennie\",\n    \"location\": \"Location\",\n    \"region\": \"Region\",\n    \"founded\": 2025,\n    \"owner\": \"MyWhiskyShelf\",\n    \"distilleryType\": \"Malt\",\n    \"flavourProfile\": {\n      \"sweet\": 4,\n      \"fruit\": 4,\n      \"floral\": 4,\n      \"body\": 4,\n      \"smoke\": 4,\n      \"tobacco\": 4,\n      \"medicinal\": 4,\n      \"wine\": 4,\n      \"spice\": 4,\n      \"malt\": 4,\n      \"nut\": 4,\n      \"honey\": 4\n    },\n    \"active\": true\n  }"
        },
        "bodyType": "application/json",
        "description": "",
        "headers": [
          {
            "enabled": true,
            "name": "Content-Type",
            "value": "application/json",
            "id": "4fQdDrbnSr"
          }
        ],
        "method": "POST",
        "name": "Add new distillery",
        "sortPriority": 1000.0,
        "url": "${[ host ]}/distilleries/add",
        "urlParameters": []
      },
      {
        "model": "http_request",
        "id": "rq_d6JbX9rTAu",
        "createdAt": "2025-07-08T15:47:41.179728",
        "updatedAt": "2025-07-10T19:58:11.948966800",
        "workspaceId": "wk_E9kD4NLtfq",
        "folderId": "fl_vr5hv9qtjH",
        "authentication": {},
        "authenticationType": null,
        "body": {},
        "bodyType": null,
        "description": "",
        "headers": [],
        "method": "GET",
        "name": "Get all distillery names",
        "sortPriority": 3000.0,
        "url": "${[ host ]}/distilleries/names",
        "urlParameters": []
      },
      {
        "model": "http_request",
        "id": "rq_Af6bdNoBJ8",
        "createdAt": "2025-07-08T15:47:04.039089800",
        "updatedAt": "2025-07-10T19:58:11.945028400",
        "workspaceId": "wk_E9kD4NLtfq",
        "folderId": "fl_vr5hv9qtjH",
        "authentication": {},
        "authenticationType": null,
        "body": {},
        "bodyType": null,
        "description": "",
        "headers": [],
        "method": "GET",
        "name": "Get all distilleries",
        "sortPriority": 2000.0,
        "url": "${[ host ]}/distilleries",
        "urlParameters": []
      }
    ],
    "grpcRequests": [],
    "websocketRequests": []
  }
}